keiconf/__about__.py
keiconf/__init__.py
keiconf/test_keiconf.py
keiconf/io/__init__.py
keiconf-0.0.1.dist-info/METADATA
keiconf-0.0.1.dist-info/WHEEL
keiconf-0.0.1.dist-info/licenses/LICENSE.txt
keiconf-0.0.1.dist-info/RECORD
